{"metadata": {"dbt_schema_version": "https://schemas.getdbt.com/dbt/run-results/v6.json", "dbt_version": "1.8.1", "generated_at": "2024-06-05T12:40:31.168920Z", "invocation_id": "62601f10-1626-47c4-8b65-165390739cac", "env": {}}, "results": [{"status": "success", "timing": [{"name": "compile", "started_at": "2024-06-05T12:40:23.853881Z", "completed_at": "2024-06-05T12:40:23.874764Z"}, {"name": "execute", "started_at": "2024-06-05T12:40:23.876766Z", "completed_at": "2024-06-05T12:40:31.158045Z"}], "thread_id": "Thread-1", "execution_time": 7.307146787643433, "adapter_response": {"_message": "CREATE TABLE (200.0 rows, 10.7 KiB processed)", "code": "CREATE TABLE", "rows_affected": 200, "bytes_processed": 10920, "bytes_billed": 20971520, "location": "US", "project_id": "wide-hold-423812-a4", "job_id": "a051389c-94a6-4a18-b127-5536d2b9d5fc", "slot_ms": 114237}, "message": "CREATE TABLE (200.0 rows, 10.7 KiB processed)", "failures": null, "unique_id": "model.domain_driven.intermediate_cust__join", "compiled": true, "compiled_code": "\n\nwith stagin1 as (\n    select * from `wide-hold-423812-a4`.`staging`.`stg_customer_add__test`\n),\nstagin2 as (\n    select * from `wide-hold-423812-a4`.`staging`.`stg_customer__test`\n)\n\nselect a.*, b.Name from\nstagin2 as a\njoin stagin1 as b\non a.CustomerID = b.CustomerID", "relation_name": "`wide-hold-423812-a4`.`intermediate`.`intermediate_cust__join`"}], "elapsed_time": 10.165486812591553, "args": {"log_level": "info", "which": "run", "target": "dev", "log_file_max_bytes": 10485760, "indirect_selection": "eager", "require_resource_names_without_spaces": false, "select": ["intermediate_cust__join"], "use_colors": true, "show_resource_report": false, "log_level_file": "debug", "quiet": false, "log_path": "C:\\Users\\FireAngel\\Desktop\\dbt_core_project\\dbt_test\\domain_driven\\logs", "introspect": true, "invocation_command": "dbt run --select intermediate_cust__join --target dev", "source_freshness_run_project_hooks": false, "print": true, "empty": false, "cache_selected_only": false, "log_format_file": "debug", "project_dir": "C:\\Users\\FireAngel\\Desktop\\dbt_core_project\\dbt_test\\domain_driven", "macro_debugging": false, "static_parser": true, "defer": false, "profiles_dir": "C:\\Users\\FireAngel\\.dbt", "write_json": true, "strict_mode": false, "log_format": "default", "require_explicit_package_overrides_for_builtin_materializations": true, "partial_parse_file_diff": true, "favor_state": false, "partial_parse": true, "use_colors_file": true, "vars": {}, "printer_width": 80, "warn_error_options": {"include": [], "exclude": []}, "send_anonymous_usage_stats": true, "populate_cache": true, "version_check": true, "exclude": [], "enable_legacy_logger": false}}